README.md
fondant/__init__.py
fondant/build.py
fondant/cli.py
fondant/component/__init__.py
fondant/component/component.py
fondant/component/data_io.py
fondant/component/executor.py
fondant/components/caption_images/fondant_component.yaml
fondant/components/chunk_text/fondant_component.yaml
fondant/components/crop_images/fondant_component.yaml
fondant/components/download_images/fondant_component.yaml
fondant/components/embed_images/fondant_component.yaml
fondant/components/embed_text/fondant_component.yaml
fondant/components/evaluate_ragas/fondant_component.yaml
fondant/components/extract_image_resolution/fondant_component.yaml
fondant/components/filter_image_resolution/fondant_component.yaml
fondant/components/filter_language/fondant_component.yaml
fondant/components/filter_text_length/fondant_component.yaml
fondant/components/generate_minhash/fondant_component.yaml
fondant/components/index_aws_opensearch/fondant_component.yaml
fondant/components/index_qdrant/fondant_component.yaml
fondant/components/index_weaviate/fondant_component.yaml
fondant/components/load_from_csv/fondant_component.yaml
fondant/components/load_from_files/fondant_component.yaml
fondant/components/load_from_hf_hub/fondant_component.yaml
fondant/components/load_from_parquet/fondant_component.yaml
fondant/components/load_from_pdf/fondant_component.yaml
fondant/components/load_from_pdf/tests/fondant_component.yaml
fondant/components/load_with_llamahub/fondant_component.yaml
fondant/components/load_with_llamahub/tests/fondant_component.yaml
fondant/components/normalize_text/fondant_component.yaml
fondant/components/resize_images/fondant_component.yaml
fondant/components/retrieve_from_weaviate/fondant_component.yaml
fondant/components/retrieve_laion_by_embedding/fondant_component.yaml
fondant/components/retrieve_laion_by_prompt/fondant_component.yaml
fondant/components/segment_images/fondant_component.yaml
fondant/components/write_to_hf_hub/fondant_component.yaml
fondant/core/__init__.py
fondant-1.0.0.dist-info/LICENSE
fondant-1.0.0.dist-info/METADATA
fondant-1.0.0.dist-info/WHEEL
fondant-1.0.0.dist-info/entry_points.txt
fondant-1.0.0.dist-info/RECORD
