Metadata-Version: 2.1
Name: fondant
Version: 1.0.0
Summary: Fondant - Large-scale data processing made easy and reusable
Home-page: https://github.com/ml6team/fondant
License: Apache-2.0
Keywords: data,machine learning,fine-tuning,foundation models
Author: ML6
Author-email: fondant@ml6.eu
Maintainer: ML6
Maintainer-email: fondant@ml6.eu
Requires-Python: >=3.8,<3.12
Classifier: Development Status :: 2 - Pre-Alpha
Classifier: Intended Audience :: Developers
Classifier: License :: OSI Approved :: Apache Software License
Classifier: Operating System :: OS Independent
Classifier: Programming Language :: Python
Classifier: Programming Language :: Python :: 3
Classifier: Programming Language :: Python :: 3.8
Classifier: Programming Language :: Python :: 3.9
Classifier: Programming Language :: Python :: 3.10
Classifier: Programming Language :: Python :: 3.11
Classifier: Programming Language :: Python :: 3 :: Only
Classifier: Topic :: Software Development
Classifier: Topic :: Software Development :: Libraries
Classifier: Topic :: Software Development :: Libraries :: Python Modules
Classifier: Typing :: Typed
Provides-Extra: aws
Provides-Extra: azure
Provides-Extra: component
Provides-Extra: docker
Provides-Extra: gcp
Provides-Extra: kfp
Provides-Extra: sagemaker
Provides-Extra: vertex
Requires-Dist: adlfs (>=2023.4.0) ; extra == "azure"
Requires-Dist: boto3 (==1.28.64) ; extra == "sagemaker"
Requires-Dist: dask[dataframe,diagnostics,distributed] (>=2023.4.1) ; extra == "component"
Requires-Dist: docker (>=6.1.3) ; extra == "kfp" or extra == "vertex" or extra == "docker"
Requires-Dist: fsspec (>=2023.4.0)
Requires-Dist: gcsfs (>=2023.10.0) ; extra == "gcp"
Requires-Dist: google-cloud-aiplatform (==1.34.0) ; extra == "vertex"
Requires-Dist: importlib-resources (>=1.3) ; python_version < "3.9"
Requires-Dist: jsonschema (>=4.18)
Requires-Dist: kfp[kubernetes] (==2.6.0) ; extra == "kfp" or extra == "vertex"
Requires-Dist: pyarrow (>=11.0.0)
Requires-Dist: pyyaml (>=5.3.1)
Requires-Dist: s3fs (>=2023.4.0) ; extra == "aws"
Requires-Dist: sagemaker (>=2.197.0) ; extra == "sagemaker"
Project-URL: Repository, https://github.com/ml6team/fondant
